cacab/__init__.py
cacab/decorator/__init__.py
cacab/decorator/main.py
cacab/plot/__init__.py
cacab/plot/main.py
cacab/tests/__init__.py
cacab/tests/test_plot_main.py
cacab-0.0.3.post5.dist-info/LICENCE
cacab-0.0.3.post5.dist-info/METADATA
cacab-0.0.3.post5.dist-info/WHEEL
cacab-0.0.3.post5.dist-info/top_level.txt
cacab-0.0.3.post5.dist-info/RECORD
