Metadata-Version: 2.1
Name: cacab
Version: 0.0.3.post5
Summary: A multi-utility package
Author-email: Casper Chris Adriaan Bekkers <casperbekkers2@hotmail.com>
Requires-Python: >=3.9
License-File: LICENCE
Requires-Dist: matplotlib
Requires-Dist: scipy
Requires-Dist: pandas
Requires-Dist: PyQt5
